{"cameraMode":{"drawMode":0,"name":"Shaded","section":"Shading Mode"},"sceneLighting":false,"audioPlay":false,"sceneViewState":{"m_AlwaysRefresh":false,"showFog":true,"showSkybox":false,"showFlares":true,"showImageEffects":true,"showParticleSystems":true,"showVisualEffectGraphs":true,"m_FxEnabled":true},"in2DMode":false,"pivot":{"x":0.0,"y":0.25356346368789675,"z":0.0},"rotation":{"x":-0.40277624130249026,"y":-0.44092026352882388,"z":0.23042921721935273,"w":-0.7686342597007752},"size":2.3277459144592287,"orthographic":false}